plottica/__about__.py
plottica/__init__.py
plottica/lineplot.py
plottica/set_theme.py
plottica-0.2.2.dist-info/METADATA
plottica-0.2.2.dist-info/WHEEL
plottica-0.2.2.dist-info/licenses/LICENSE
plottica-0.2.2.dist-info/RECORD
