Metadata-Version: 2.4
Name: plottica
Version: 0.2.2
Summary: A shortcut package for academic plotting.
Project-URL: Documentation, https://github.com/LovelyBuggies/plottica#readme
Project-URL: Issues, https://github.com/LovelyBuggies/plottica/issues
Project-URL: Source, https://github.com/LovelyBuggies/plottica
Author-email: Shuo Liu <ninomyemail@gmail.com>
License-Expression: MIT
License-File: LICENSE
Keywords: Academic,Plotting,Research
Classifier: Development Status :: 4 - Beta
Classifier: Programming Language :: Python
Classifier: Programming Language :: Python :: 3.10
Classifier: Programming Language :: Python :: 3.11
Classifier: Programming Language :: Python :: 3.12
Classifier: Programming Language :: Python :: Implementation :: CPython
Classifier: Programming Language :: Python :: Implementation :: PyPy
Requires-Python: >=3.10
Requires-Dist: matplotlib>=3.4.0
Requires-Dist: numpy>=1.21.0
Requires-Dist: pandas>=1.3.0
Requires-Dist: seaborn>=0.11.0
Provides-Extra: dev
Requires-Dist: black>=24.2.0; extra == 'dev'
Requires-Dist: build>=0.7.0; extra == 'dev'
Requires-Dist: jupyter-book>=1.0.3; extra == 'dev'
Requires-Dist: jupyter-notebook>=7.3.2; extra == 'dev'
Requires-Dist: jupyterlab>=1.1.1; extra == 'dev'
Requires-Dist: pre-commit>=2.15.0; extra == 'dev'
Requires-Dist: pytest>=8.3.4; extra == 'dev'
Requires-Dist: scipy>=1.15.2; extra == 'dev'
Requires-Dist: twine>=3.4.0; extra == 'dev'
Requires-Dist: wandb>=0.19.7; extra == 'dev'
